<?xml version="1.0" encoding="UTF-8"?>
<record_update sys_domain="global" table="pa_dimensions">
    <pa_dimensions action="INSERT_OR_UPDATE">
        <active>true</active>
        <conditions table="sys_choice">name=x_224218_itsom_to_do_list^element=state^inactive=false^language=en<item endquery="false" field="name" goto="false" newquery="false" operator="=" or="false" value="x_224218_itsom_to_do_list"/>
            <item endquery="false" field="element" goto="false" newquery="false" operator="=" or="false" value="state"/>
            <item endquery="false" field="inactive" goto="false" newquery="false" operator="=" or="false" value="false"/>
            <item endquery="false" field="language" goto="false" newquery="false" operator="=" or="false" value="en"/>
        </conditions>
        <description/>
        <empty_value/>
        <facts_table>sys_choice</facts_table>
        <field>sys_id</field>
        <manual_breakdown/>
        <name>ToDoList.States</name>
        <security_type>1</security_type>
        <sys_class_name>pa_dimensions</sys_class_name>
        <sys_created_by>saurav.sarkar</sys_created_by>
        <sys_created_on>2018-06-03 05:27:45</sys_created_on>
        <sys_domain>global</sys_domain>
        <sys_domain_path>/</sys_domain_path>
        <sys_id>f99ec5d44fa6d700aa252ed18110c752</sys_id>
        <sys_mod_count>0</sys_mod_count>
        <sys_name>ToDoList.States</sys_name>
        <sys_overrides/>
        <sys_package display_value="IT services operation management" source="x_224218_itsom">6fd1341c4f4e9300aa252ed18110c744</sys_package>
        <sys_policy/>
        <sys_scope display_value="IT services operation management">6fd1341c4f4e9300aa252ed18110c744</sys_scope>
        <sys_update_name>pa_dimensions_f99ec5d44fa6d700aa252ed18110c752</sys_update_name>
        <sys_updated_by>saurav.sarkar</sys_updated_by>
        <sys_updated_on>2018-06-03 05:27:45</sys_updated_on>
    </pa_dimensions>
    <sys_translated_text action="delete_multiple" query="documentkey=f99ec5d44fa6d700aa252ed18110c752"/>
</record_update>
